autowatch
