Metadata-Version: 1.1
Name: autowatch
Version: 1.1.0
Summary: Auto Watch
Home-page: http://www.thbin.org/
Author: JoeLei
Author-email: thezero12@hotmail.com
License: UNKNOWN
Platform: UNKNOWN
Classifier: Intended Audience :: Information Technology
Classifier: Intended Audience :: System Administrators
Classifier: License :: OSI Approved :: Apache Software License
Classifier: Operating System :: POSIX :: Linux
Classifier: Programming Language :: Python
Classifier: Programming Language :: Python :: 2
Classifier: Programming Language :: Python :: 2.7
Classifier: Topic :: System :: Monitoring
